{
	"name": "models/humans_r5/pilots_r5/pilot_revenant/skins/common/revenant_gauntlet_common_colpass",
	"width": 1024,
	"height": 1024,
	"depth": 0,
	"glueFlags": "0x561404a0",
	"glueFlags2": "0x0",
	"blendStates": [
		"0xF0000000",
		"0xF0000000",
		"0xF0000000",
		"0xF0000000",
		"0xF0000000",
		"0xF0000000",
		"0xF0000000",
		"0xF0000000"
	],
	"blendStateMask": "0x4",
	"depthStencilFlags": "0x5",
	"rasterizerFlags": "0x2",
	"uberBufferFlags": "0x0",
	"features": "0x1F5A92BD",
	"samplers": "0x1D0300",
	"surfaceProp": "flesh",
	"surfaceProp2": "",
	"shaderType": "sknp",
	"shaderSet": "0x2443033BA9B110D1",
	"$textures": {
		"0": "0x61AFC344CC778A98",
		"1": "0x6015A0135C19F048",
		"2": "0xA23061CEFF3D88A3",
		"3": "0xCEE33CDA0B581B5C",
		"4": "0x2816F20B5FAB2FCF",
		"5": "0xC99951A62E09C381",
		"6": "0x7C591C4975BF4558",
		"7": "0xF8515377F27124FC",
		"8": "0xC6CEF2805D9912E7"
	},
	"$depthShadowMaterial": "0x38986BFEE0C0045",
	"$depthPrepassMaterial": "0xC57DD2E270416870",
	"$depthVSMMaterial": "0x91948E27A08AEAC0",
	"$depthShadowTightMaterial": "0x2F0587828392902",
	"$colpassMaterial": "0x0",
	"$textureAnimation": "0x0"
}
