{
	"name": "models/humans_r5/pilots_r5/pilot_revenant/skins/egyptian_rt_01/revenant_viewmodel_tactical_egyptian_rt_01",
	"width": 1024,
	"height": 1024,
	"depth": 0,
	"glueFlags": "0x56100420",
	"glueFlags2": "0x0",
	"blendStates": [
		"0xF0000000",
		"0xF0000000",
		"0xF0000000",
		"0xF0000000",
		"0xF0000000",
		"0xF0000000",
		"0xF0000000",
		"0xF0000000"
	],
	"blendStateMask": "0x4",
	"depthStencilFlags": "0x17",
	"rasterizerFlags": "0x6",
	"uberBufferFlags": "0x0",
	"features": "0x1F5A92BD",
	"samplers": "0x1D0300",
	"surfaceProp": "flesh",
	"surfaceProp2": "",
	"shaderType": "sknp",
	"shaderSet": "0xFAD52F647ABC6391",
	"$textures": {
		"0": "0x2A7431EE446FE621",
		"1": "0x3C844E5DE3106A92",
		"2": "0x47F2CE169DD85310",
		"3": "0xEDA3492AA927217",
		"4": "0xDDB83117107543E0",
		"5": "0x9574D5E80FA893EB",
		"6": "0x2B89F4540DB65315"
	},
	"$depthShadowMaterial": "0x2041FBA757739DEC",
	"$depthPrepassMaterial": "0x10D9C6045C7BD4E",
	"$depthVSMMaterial": "0xE19C98FEDA9DEAA",
	"$depthShadowTightMaterial": "0xA9F3790995D7164B",
	"$colpassMaterial": "0xECED6D61971AC448",
	"$textureAnimation": "0x0"
}
